{
    "swagger": "2.0",
    "info": {
        "description": "This is a sample server celler server.",
        "title": "Swagger Example API",
        "termsOfService": "http://swagger.io/terms/",
        "contact": {
            "name": "API Support",
            "url": "http://www.swagger.io/support",
            "email": "support@swagger.io"
        },
        "license": {
            "name": "Apache 2.0",
            "url": "http://www.apache.org/licenses/LICENSE-2.0.html"
        },
        "version": "1.0"
    },
    "host": "localhost",
    "basePath": "/api/v1",
    "paths": {
        "/authors": {
            "get": {
                "consumes": [
                    "application/json"
                ],
                "produces": [
                    "application/json"
                ],
                "tags": [
                    "authors"
                ],
                "summary": "List of authors from the store",
                "responses": {
                    "200": {
                        "description": "OK",
                        "schema": {
                            "type": "array",
                            "items": {
                                "$ref": "#/definitions/author.Response"
                            }
                        }
                    },
                    "500": {
                        "description": "Internal Server Error",
                        "schema": {
                            "$ref": "#/definitions/status.Response"
                        }
                    }
                }
            },
            "post": {
                "consumes": [
                    "application/json"
                ],
                "produces": [
                    "application/json"
                ],
                "tags": [
                    "authors"
                ],
                "summary": "Add a new author to the store",
                "parameters": [
                    {
                        "description": "body param",
                        "name": "request",
                        "in": "body",
                        "required": true,
                        "schema": {
                            "$ref": "#/definitions/author.Request"
                        }
                    }
                ],
                "responses": {
                    "200": {
                        "description": "OK",
                        "schema": {
                            "$ref": "#/definitions/author.Response"
                        }
                    },
                    "400": {
                        "description": "Bad Request",
                        "schema": {
                            "$ref": "#/definitions/status.Response"
                        }
                    },
                    "500": {
                        "description": "Internal Server Error",
                        "schema": {
                            "$ref": "#/definitions/status.Response"
                        }
                    }
                }
            }
        },
        "/authors/{id}": {
            "get": {
                "consumes": [
                    "application/json"
                ],
                "produces": [
                    "application/json"
                ],
                "tags": [
                    "authors"
                ],
                "summary": "Read the author from the store",
                "parameters": [
                    {
                        "type": "integer",
                        "description": "path param",
                        "name": "id",
                        "in": "path",
                        "required": true
                    }
                ],
                "responses": {
                    "200": {
                        "description": "OK",
                        "schema": {
                            "$ref": "#/definitions/author.Response"
                        }
                    },
                    "500": {
                        "description": "Internal Server Error",
                        "schema": {
                            "$ref": "#/definitions/status.Response"
                        }
                    }
                }
            },
            "put": {
                "consumes": [
                    "application/json"
                ],
                "produces": [
                    "application/json"
                ],
                "tags": [
                    "authors"
                ],
                "summary": "Update the author in the store",
                "parameters": [
                    {
                        "type": "integer",
                        "description": "path param",
                        "name": "id",
                        "in": "path",
                        "required": true
                    },
                    {
                        "description": "body param",
                        "name": "request",
                        "in": "body",
                        "required": true,
                        "schema": {
                            "$ref": "#/definitions/author.Request"
                        }
                    }
                ],
                "responses": {
                    "200": {
                        "description": "OK"
                    },
                    "400": {
                        "description": "Bad Request",
                        "schema": {
                            "$ref": "#/definitions/status.Response"
                        }
                    },
                    "500": {
                        "description": "Internal Server Error",
                        "schema": {
                            "$ref": "#/definitions/status.Response"
                        }
                    }
                }
            },
            "delete": {
                "consumes": [
                    "application/json"
                ],
                "produces": [
                    "application/json"
                ],
                "tags": [
                    "authors"
                ],
                "summary": "Delete the author from the store",
                "parameters": [
                    {
                        "type": "integer",
                        "description": "path param",
                        "name": "id",
                        "in": "path",
                        "required": true
                    }
                ],
                "responses": {
                    "200": {
                        "description": "OK"
                    },
                    "500": {
                        "description": "Internal Server Error",
                        "schema": {
                            "$ref": "#/definitions/status.Response"
                        }
                    }
                }
            }
        },
        "/books": {
            "get": {
                "consumes": [
                    "application/json"
                ],
                "produces": [
                    "application/json"
                ],
                "tags": [
                    "books"
                ],
                "summary": "List of books from the store",
                "responses": {
                    "200": {
                        "description": "OK",
                        "schema": {
                            "type": "array",
                            "items": {
                                "$ref": "#/definitions/book.Response"
                            }
                        }
                    },
                    "500": {
                        "description": "Internal Server Error",
                        "schema": {
                            "$ref": "#/definitions/status.Response"
                        }
                    }
                }
            },
            "post": {
                "consumes": [
                    "application/json"
                ],
                "produces": [
                    "application/json"
                ],
                "tags": [
                    "books"
                ],
                "summary": "Add a new book to the store",
                "parameters": [
                    {
                        "description": "body param",
                        "name": "request",
                        "in": "body",
                        "required": true,
                        "schema": {
                            "$ref": "#/definitions/book.Request"
                        }
                    }
                ],
                "responses": {
                    "200": {
                        "description": "OK",
                        "schema": {
                            "$ref": "#/definitions/book.Response"
                        }
                    },
                    "400": {
                        "description": "Bad Request",
                        "schema": {
                            "$ref": "#/definitions/status.Response"
                        }
                    },
                    "500": {
                        "description": "Internal Server Error",
                        "schema": {
                            "$ref": "#/definitions/status.Response"
                        }
                    }
                }
            }
        },
        "/books/{id}": {
            "get": {
                "consumes": [
                    "application/json"
                ],
                "produces": [
                    "application/json"
                ],
                "tags": [
                    "books"
                ],
                "summary": "Read the book from the store",
                "parameters": [
                    {
                        "type": "integer",
                        "description": "path param",
                        "name": "id",
                        "in": "path",
                        "required": true
                    }
                ],
                "responses": {
                    "200": {
                        "description": "OK",
                        "schema": {
                            "$ref": "#/definitions/book.Response"
                        }
                    },
                    "500": {
                        "description": "Internal Server Error",
                        "schema": {
                            "$ref": "#/definitions/status.Response"
                        }
                    }
                }
            },
            "put": {
                "consumes": [
                    "application/json"
                ],
                "produces": [
                    "application/json"
                ],
                "tags": [
                    "books"
                ],
                "summary": "Update the book in the store",
                "parameters": [
                    {
                        "type": "integer",
                        "description": "path param",
                        "name": "id",
                        "in": "path",
                        "required": true
                    },
                    {
                        "description": "body param",
                        "name": "request",
                        "in": "body",
                        "required": true,
                        "schema": {
                            "$ref": "#/definitions/book.Request"
                        }
                    }
                ],
                "responses": {
                    "200": {
                        "description": "OK"
                    },
                    "400": {
                        "description": "Bad Request",
                        "schema": {
                            "$ref": "#/definitions/status.Response"
                        }
                    },
                    "500": {
                        "description": "Internal Server Error",
                        "schema": {
                            "$ref": "#/definitions/status.Response"
                        }
                    }
                }
            },
            "delete": {
                "consumes": [
                    "application/json"
                ],
                "produces": [
                    "application/json"
                ],
                "tags": [
                    "books"
                ],
                "summary": "Delete the book from the store",
                "parameters": [
                    {
                        "type": "integer",
                        "description": "path param",
                        "name": "id",
                        "in": "path",
                        "required": true
                    }
                ],
                "responses": {
                    "200": {
                        "description": "OK"
                    },
                    "500": {
                        "description": "Internal Server Error",
                        "schema": {
                            "$ref": "#/definitions/status.Response"
                        }
                    }
                }
            }
        },
        "/books/{id}/authors": {
            "get": {
                "consumes": [
                    "application/json"
                ],
                "produces": [
                    "application/json"
                ],
                "tags": [
                    "books"
                ],
                "summary": "List of authors from the store",
                "parameters": [
                    {
                        "type": "integer",
                        "description": "path param",
                        "name": "id",
                        "in": "path",
                        "required": true
                    }
                ],
                "responses": {
                    "200": {
                        "description": "OK",
                        "schema": {
                            "type": "array",
                            "items": {
                                "$ref": "#/definitions/author.Response"
                            }
                        }
                    },
                    "500": {
                        "description": "Internal Server Error",
                        "schema": {
                            "$ref": "#/definitions/status.Response"
                        }
                    }
                }
            }
        },
        "/members": {
            "get": {
                "consumes": [
                    "application/json"
                ],
                "produces": [
                    "application/json"
                ],
                "tags": [
                    "members"
                ],
                "summary": "List of members from the store",
                "responses": {
                    "200": {
                        "description": "OK",
                        "schema": {
                            "type": "array",
                            "items": {
                                "$ref": "#/definitions/member.Response"
                            }
                        }
                    },
                    "500": {
                        "description": "Internal Server Error",
                        "schema": {
                            "$ref": "#/definitions/status.Response"
                        }
                    }
                }
            },
            "post": {
                "consumes": [
                    "application/json"
                ],
                "produces": [
                    "application/json"
                ],
                "tags": [
                    "members"
                ],
                "summary": "Add a new member to the store",
                "parameters": [
                    {
                        "description": "body param",
                        "name": "request",
                        "in": "body",
                        "required": true,
                        "schema": {
                            "$ref": "#/definitions/member.Request"
                        }
                    }
                ],
                "responses": {
                    "200": {
                        "description": "OK",
                        "schema": {
                            "$ref": "#/definitions/member.Response"
                        }
                    },
                    "400": {
                        "description": "Bad Request",
                        "schema": {
                            "$ref": "#/definitions/status.Response"
                        }
                    },
                    "500": {
                        "description": "Internal Server Error",
                        "schema": {
                            "$ref": "#/definitions/status.Response"
                        }
                    }
                }
            }
        },
        "/members/{id}": {
            "get": {
                "consumes": [
                    "application/json"
                ],
                "produces": [
                    "application/json"
                ],
                "tags": [
                    "members"
                ],
                "summary": "Read the member from the store",
                "parameters": [
                    {
                        "type": "integer",
                        "description": "path param",
                        "name": "id",
                        "in": "path",
                        "required": true
                    }
                ],
                "responses": {
                    "200": {
                        "description": "OK",
                        "schema": {
                            "$ref": "#/definitions/member.Response"
                        }
                    },
                    "500": {
                        "description": "Internal Server Error",
                        "schema": {
                            "$ref": "#/definitions/status.Response"
                        }
                    }
                }
            },
            "put": {
                "consumes": [
                    "application/json"
                ],
                "produces": [
                    "application/json"
                ],
                "tags": [
                    "members"
                ],
                "summary": "Update the member in the store",
                "parameters": [
                    {
                        "type": "integer",
                        "description": "path param",
                        "name": "id",
                        "in": "path",
                        "required": true
                    },
                    {
                        "description": "body param",
                        "name": "request",
                        "in": "body",
                        "required": true,
                        "schema": {
                            "$ref": "#/definitions/member.Request"
                        }
                    }
                ],
                "responses": {
                    "200": {
                        "description": "OK"
                    },
                    "400": {
                        "description": "Bad Request",
                        "schema": {
                            "$ref": "#/definitions/status.Response"
                        }
                    },
                    "500": {
                        "description": "Internal Server Error",
                        "schema": {
                            "$ref": "#/definitions/status.Response"
                        }
                    }
                }
            },
            "delete": {
                "consumes": [
                    "application/json"
                ],
                "produces": [
                    "application/json"
                ],
                "tags": [
                    "members"
                ],
                "summary": "Delete the member from the store",
                "parameters": [
                    {
                        "type": "integer",
                        "description": "path param",
                        "name": "id",
                        "in": "path",
                        "required": true
                    }
                ],
                "responses": {
                    "200": {
                        "description": "OK"
                    },
                    "500": {
                        "description": "Internal Server Error",
                        "schema": {
                            "$ref": "#/definitions/status.Response"
                        }
                    }
                }
            }
        },
        "/members/{id}/books": {
            "get": {
                "consumes": [
                    "application/json"
                ],
                "produces": [
                    "application/json"
                ],
                "tags": [
                    "members"
                ],
                "summary": "List of books from the store",
                "parameters": [
                    {
                        "type": "integer",
                        "description": "path param",
                        "name": "id",
                        "in": "path",
                        "required": true
                    }
                ],
                "responses": {
                    "200": {
                        "description": "OK",
                        "schema": {
                            "type": "array",
                            "items": {
                                "$ref": "#/definitions/book.Response"
                            }
                        }
                    },
                    "500": {
                        "description": "Internal Server Error",
                        "schema": {
                            "$ref": "#/definitions/status.Response"
                        }
                    }
                }
            }
        }
    },
    "definitions": {
        "author.Request": {
            "type": "object",
            "properties": {
                "fullName": {
                    "type": "string"
                },
                "pseudonym": {
                    "type": "string"
                },
                "specialty": {
                    "type": "string"
                }
            }
        },
        "author.Response": {
            "type": "object",
            "properties": {
                "fullName": {
                    "type": "string"
                },
                "id": {
                    "type": "string"
                },
                "pseudonym": {
                    "type": "string"
                },
                "specialty": {
                    "type": "string"
                }
            }
        },
        "book.Request": {
            "type": "object",
            "required": [
                "authors",
                "genre",
                "isbn",
                "name"
            ],
            "properties": {
                "authors": {
                    "type": "array",
                    "items": {
                        "type": "string"
                    }
                },
                "genre": {
                    "type": "string"
                },
                "id": {
                    "type": "string"
                },
                "isbn": {
                    "type": "string"
                },
                "name": {
                    "type": "string"
                }
            }
        },
        "book.Response": {
            "type": "object",
            "properties": {
                "authors": {
                    "type": "array",
                    "items": {
                        "type": "string"
                    }
                },
                "genre": {
                    "type": "string"
                },
                "id": {
                    "type": "string"
                },
                "isbn": {
                    "type": "string"
                },
                "name": {
                    "type": "string"
                }
            }
        },
        "member.Request": {
            "type": "object",
            "required": [
                "books",
                "fullName"
            ],
            "properties": {
                "books": {
                    "type": "array",
                    "items": {
                        "type": "string"
                    }
                },
                "fullName": {
                    "type": "string"
                },
                "id": {
                    "type": "string"
                }
            }
        },
        "member.Response": {
            "type": "object",
            "properties": {
                "books": {
                    "type": "array",
                    "items": {
                        "type": "string"
                    }
                },
                "fullName": {
                    "type": "string"
                },
                "id": {
                    "type": "string"
                }
            }
        },
        "status.Response": {
            "type": "object",
            "properties": {
                "data": {},
                "message": {
                    "type": "string"
                },
                "success": {
                    "type": "boolean"
                }
            }
        }
    }
}